django_dataclass_forms/__init__.py
django_dataclass_forms/form.py
django_dataclass_forms-0.1.1.dist-info/LICENSE
django_dataclass_forms-0.1.1.dist-info/METADATA
django_dataclass_forms-0.1.1.dist-info/WHEEL
django_dataclass_forms-0.1.1.dist-info/RECORD
